transliteration_ua.py
transliteration_ua-0.2.0.dist-info/LICENSE
transliteration_ua-0.2.0.dist-info/METADATA
transliteration_ua-0.2.0.dist-info/WHEEL
transliteration_ua-0.2.0.dist-info/RECORD
